{"$schema":"https://json-schema.org/draft/2020-12/schema","title":"GlobalConfig","type":"object","properties":{"databases":{"type":"object","additionalProperties":{"$ref":"#/$defs/GlobalDatabaseConfig"}}},"required":["databases"],"$defs":{"GlobalDatabaseConfig":{"anyOf":[{"$ref":"#/$defs/GlobalConfigInflux"}]},"GlobalConfigInflux":{"type":"object","properties":{"type":{"$ref":"#/$defs/DatabaseTypeInflux"},"url":{"type":"string"},"token":{"type":"string"}},"required":["type","url","token"]},"DatabaseTypeInflux":{"type":"string","enum":["influxdb"]}}}